{
  "name": "Mailpile (Chelsea)",
  "authors": ["The Mailpile Team <team@mailpile.is>"],
  "icons": [
    "icon-comment",
    "icon-forum",
    "icon-donate",
    "icon-news",
    "icon-photos",
    "icon-image",
    "icon-video",
    "icon-themes",
    "icon-links",
    "icon-document",
    "icon-text",
    "icon-travel",
    "icon-money",
    "icon-receipts",
    "icon-trophy",
    "icon-calendar",
    "icon-spreadsheet",
    "icon-attachment",
    "icon-user",
    "icon-groups",
    "icon-graph",
    "icon-list",
    "icon-checkmark",
    "icon-alerts",
    "icon-zip",
    "icon-work",
    "icon-star",
    "icon-rss",
    "icon-robot",
    "icon-code",
    "icon-privacy",
    "icon-music",
    "icon-lock-closed",
    "icon-key",
    "icon-home",
    "icon-new",
    "icon-compose",
    "icon-inbox",
    "icon-sent",
    "icon-outbox",
    "icon-spam",
    "icon-trash"
  ],
  "colors": {
    "white": "#ffffff", 
    "gray-light": "#f6f6f6", 
    "gray-mid": "#cccccc",
    "gray": "#b3b3b3",
    "gray-dark": "#4d4d4d",
    "black": "#333333",
    "blue-light" : "#85b2e8",
    "blue": "#337fb2",
    "green-light": "#a3ce73",
    "green": "#4b9441",
    "yellow": "#e9db2f",
    "orange": "#fbb03b",
    "orange-red": "#f15a24",
    "red": "#be1c21",
    "brown": "#7d4837",
    "brown-light": "#90746c",
    "pink": "#f08dca",
    "purple": "#6a27a4"
  }
}